tunafish/__init__.py
tunafish/evolution/__init__.py
tunafish/evolution/automatic_function.py
tunafish/evolution/util.py
tunafish/examples/__init__.py
tunafish/examples/evolution/__init__.py
tunafish/examples/evolution/biological.py
tunafish/examples/evolution/regression.py
tunafish/examples/tuning/__init__.py
tunafish/examples/tuning/basic.py
tunafish/examples/tuning/basic_with_kwargs.py
tunafish/examples/tuning/early_stopping.py
tunafish/tuning/__init__.py
tunafish/tuning/arguments.py
tunafish/tuning/function_tuner.py
tunafish/tuning/genetic_algorithm.py
tunafish/tuning/parameter_specification.py
tunafish-0.0.3.dist-info/LICENSE
tunafish-0.0.3.dist-info/METADATA
tunafish-0.0.3.dist-info/WHEEL
tunafish-0.0.3.dist-info/top_level.txt
tunafish-0.0.3.dist-info/RECORD
