Metadata-Version: 2.1
Name: tunafish
Version: 0.0.3
Summary: Tunafish is an autotuner for plain ol' Python functions. Under the hood, it uses genetic algorithms to determine which arguments maximize a function's return value (i.e. it's fitness); however, Tunafish eliminates the need to think about genetic algorithms. Instead, you can focus more on just writing code.
Home-page: https://github.com/gigaquads/tunafish.git
Author: Gigaquads
Author-email: what@gigaquads.com
License: UNKNOWN
Platform: UNKNOWN
Classifier: Programming Language :: Python :: 3.9
Requires-Dist: numpy
Requires-Dist: geap
Requires-Dist: pytest
